RTL/single_cycle_core/opcodes.svh
`ifndef OPCODES_SVH
`define OPCODES_SVH

// - - - - - R-TYPE OPCODES - - - - - //
parameter R_TYPE_OPCODE = 7'b0110011;   

// - - - - - I-TYPE OPCODES - - - - - //
parameter I_LOAD_OPCODE = 7'b0000011;
parameter I_ARITH_OPCODE = 7'b0010011;
parameter I_SHIFT_OPCODE = 7'b0010011;
parameter JALR_OPCODE = 7'b1100111;

// - - - - - S-TYPE OPCODES - - - - - //
parameter S_TYPE_OPCODE = 7'b0100011;                          

// - - - - - B-TYPE OPCODES - - - - - //
parameter B_TYPE_OPCODE = 7'b1100011;          

// - - - - - U-TYPE OPCODES - - - - - // 
parameter LUI_OPCODE = 7'b0110111;
parameter AUIPC_OPCODE = 7'b0010111;

// - - - - - J-TYPE OPCODES - - - - - //
parameter JAL_OPCODE = 7'b1101111;

`endif

RTL/single_cycle_core/immediate_gen.sv
// - - - - - IMMEDIATE GENERATOR - - - - - //
`include "opcodes.svh"

module immediate_gen (
    input logic [6:0] i_opcode,
    input logic [31:0] i_instr,
    output logic [31:0] o_ext_imm
);

    always @(*) begin
        case (i_opcode)

            // I-type immediate handling
            I_LOAD_OPCODE, I_ARITH_OPCODE, I_SHIFT_OPCODE, JALR_OPCODE: 
                o_ext_imm = {{20{i_instr[31]}}, {i_instr[31:20]}}; 

            // S-type immediate handling
            S_TYPE_OPCODE: 
                o_ext_imm = {{20{i_instr[31]}}, {i_instr[31:25]}, {i_instr[11:7]}};
            
            // B-type immediate handling
            B_TYPE_OPCODE: 
                o_ext_imm = {{20{i_instr[31]}}, {i_instr[7]}, {i_instr[30:25], i_instr[11:8]}, {1'b0}};
            
            // U-type immediate handling
            LUI_OPCODE, AUIPC_OPCODE: 
                o_ext_imm = {{i_instr[31:12]}, {12'd0}};

            // J-type immediate handling
            JAL_OPCODE: 
                o_ext_imm = {{11{i_instr[31]}}, {i_instr[31]}, {i_instr[19:12]}, {i_instr[20]}, {i_instr[30:21]}, {1'b0}};
            
            // default to no extension
            default: o_ext_imm = 32'd0;
        endcase
    end
endmodule

RTL/single_cycle_core/immediate_gen_tb.sv
// - - - - - IMMEDIATE GENERATOR TESTBENCH - - - - - //
module immediate_gen_tb;
    
    // DUT I/O signals
    logic [6:0] i_opcode;
    logic [31:0] i_instr;
    logic [31:0] o_ext_imm;
    
    // test tracking variables
    integer num_tests = 0;
    integer num_passes = 0;
    
    // DUT instantiation
    immediate_gen dut(.i_opcode(i_opcode), .i_instr(i_instr), .o_ext_imm(o_ext_imm));
    
    // test to examine whether or not the proper immediate has been generated
    task automatic check_imm;
        
        // inputs
        input [31:0] instruction;
        input [6:0] opcode;
        input [31:0] expected;
        input string inst_type;
        
        // implement
        begin
            num_tests++;
            i_instr = instruction;
            i_opcode = opcode;
            #5;
            if (o_ext_imm === expected) begin
                num_passes++;
                $display("PASS: %s - Expected: %0d, Got: %0d", inst_type, expected, o_ext_imm);
            end else begin
                $display("FAIL: %s - Expected: %0d, Got: %0d", inst_type, expected, o_ext_imm);
            end
        end
    endtask
    
    // stimulus generation
    initial begin

        // setup waveform dumping
        $dumpfile("immediate_gen.vcd");
        $dumpvars(0, immediate_gen_tb);
        $display("");

        // - - - - TEST BEGIN (Vectors generated with GPT) - - - - - // 

        // I-type Instructions
        check_imm(32'b000000000011_00001_000_00010_0000011, I_LOAD_OPCODE, 3, "I-type (LW)");
        check_imm(32'b111111111111_00001_000_00010_0010011, I_ARITH_OPCODE, -1, "I-type (ADDI negative)");
        check_imm(32'b000000000100_00001_000_00001_1100111, JALR_OPCODE, 4, "JALR (I-type)");       

        // S-type Instructions
        check_imm(32'b0000000_00010_00001_010_00100_0100011, S_TYPE_OPCODE, 4, "S-type (SW)");
        
        // B-type Instructions
        check_imm(32'b0_000000_00010_00001_000_0100_0_1100011, B_TYPE_OPCODE, 8, "B-type (BEQ)");
        
        // U-type Instructions
        check_imm(32'b00000000000000000001_00001_0110111, LUI_OPCODE, 4096, "U-type (LUI)");
        check_imm(32'b00000000000000000001_00001_0010111, AUIPC_OPCODE, 4096, "U-type (AUIPC)");
        
        // J-type Instructions
        check_imm(32'b0_0000001000_0_00000000_00001_1101111, JAL_OPCODE, 512, "J-type (JAL)");
        
        // report results
        $display("\nTest Summary:");
        $display("Passed %0d of %0d tests", num_passes, num_tests);
        if (num_passes == num_tests)
            $display("ALL TESTS PASSED!\n");
        else
            $display("SOME TESTS FAILED!\n");

        // test complete 
        $finish;
    end
endmodule

RTL/single_cycle_core/immediate_gen.vcd
$date
	Thu Jan 23 00:49:56 2025
$end
$version
	Icarus Verilog
$end
$timescale
	1s
$end
$scope module immediate_gen_tb $end
$var wire 32 ! o_ext_imm [31:0] $end
$var reg 32 " i_instr [31:0] $end
$var reg 7 # i_opcode [6:0] $end
$var integer 32 $ num_passes [31:0] $end
$var integer 32 % num_tests [31:0] $end
$scope module dut $end
$var wire 32 & i_instr [31:0] $end
$var wire 7 ' i_opcode [6:0] $end
$var reg 32 ( o_ext_imm [31:0] $end
$upscope $end
$scope task check_imm $end
$upscope $end
$upscope $end
$enddefinitions $end
$comment Show the parameter values. $end
$dumpall
$end
#0
$dumpvars
b11 (
b11 '
b1100001000000100000011 &
b1 %
b0 $
b11 #
b1100001000000100000011 "
b11 !
$end
#5
b11111111111111111111111111111111 !
b11111111111111111111111111111111 (
b10011 #
b10011 '
b11111111111100001000000100010011 "
b11111111111100001000000100010011 &
b10 %
b1 $
#10
b100 !
b100 (
b1100111 #
b1100111 '
b10000001000000011100111 "
b10000001000000011100111 &
b11 %
b10 $
#15
b100011 #
b100011 '
b1000001010001000100011 "
b1000001010001000100011 &
b100 %
b11 $
#20
b1000 !
b1000 (
b1100011 #
b1100011 '
b1000001000010001100011 "
b1000001000010001100011 &
b101 %
b100 $
#25
b1000000000000 !
b1000000000000 (
b110111 #
b110111 '
b1000010110111 "
b1000010110111 &
b110 %
b101 $
#30
b10111 #
b10111 '
b1000010010111 "
b1000010010111 &
b111 %
b110 $
#35
b10000 !
b10000 (
b1101111 #
b1101111 '
b1000000000000000011101111 "
b1000000000000000011101111 &
b1000 %
b111 $
